diagramagic-0.1.5.dist-info/METADATA
diagramagic-0.1.5.dist-info/WHEEL
diagramagic-0.1.5.dist-info/entry_points.txt
diagramagic-0.1.5.dist-info/licenses/LICENSE
diagramagic/__init__.py
diagramagic/_diagramagic_resvg.cpython-311-darwin.so
diagramagic/cli.py
diagramagic/data/AGENTS.md
diagramagic/data/PROJECTSPEC.md
diagramagic/data/README.md
diagramagic/diagramagic.py
diagramagic/resources.py
diagramagic-0.1.5.dist-info/RECORD
