Metadata-Version: 2.4
Name: diagramagic
Version: 0.1.5
Requires-Dist: pillow>=10.0.0
License-File: LICENSE
Summary: svg++ reference renderer
Requires-Python: >=3.9
